odoo/addons/sale_rental/README.rst
odoo/addons/sale_rental/__init__.py
odoo/addons/sale_rental/__manifest__.py
odoo/addons/sale_rental/hooks.py
odoo/addons/sale_rental/data/rental_data.xml
odoo/addons/sale_rental/demo/rental_demo.xml
odoo/addons/sale_rental/i18n/am.po
odoo/addons/sale_rental/i18n/ar.po
odoo/addons/sale_rental/i18n/bg.po
odoo/addons/sale_rental/i18n/bs.po
odoo/addons/sale_rental/i18n/ca.po
odoo/addons/sale_rental/i18n/ca_ES.po
odoo/addons/sale_rental/i18n/cs.po
odoo/addons/sale_rental/i18n/da.po
odoo/addons/sale_rental/i18n/de.po
odoo/addons/sale_rental/i18n/el_GR.po
odoo/addons/sale_rental/i18n/en_GB.po
odoo/addons/sale_rental/i18n/es.po
odoo/addons/sale_rental/i18n/es_AR.po
odoo/addons/sale_rental/i18n/es_CL.po
odoo/addons/sale_rental/i18n/es_CO.po
odoo/addons/sale_rental/i18n/es_CR.po
odoo/addons/sale_rental/i18n/es_DO.po
odoo/addons/sale_rental/i18n/es_EC.po
odoo/addons/sale_rental/i18n/es_ES.po
odoo/addons/sale_rental/i18n/es_MX.po
odoo/addons/sale_rental/i18n/es_PE.po
odoo/addons/sale_rental/i18n/es_PY.po
odoo/addons/sale_rental/i18n/es_VE.po
odoo/addons/sale_rental/i18n/et.po
odoo/addons/sale_rental/i18n/eu.po
odoo/addons/sale_rental/i18n/fa.po
odoo/addons/sale_rental/i18n/fi.po
odoo/addons/sale_rental/i18n/fr.po
odoo/addons/sale_rental/i18n/fr_CA.po
odoo/addons/sale_rental/i18n/fr_CH.po
odoo/addons/sale_rental/i18n/fr_FR.po
odoo/addons/sale_rental/i18n/gl.po
odoo/addons/sale_rental/i18n/gl_ES.po
odoo/addons/sale_rental/i18n/he.po
odoo/addons/sale_rental/i18n/hr.po
odoo/addons/sale_rental/i18n/hr_HR.po
odoo/addons/sale_rental/i18n/hu.po
odoo/addons/sale_rental/i18n/id.po
odoo/addons/sale_rental/i18n/it.po
odoo/addons/sale_rental/i18n/ja.po
odoo/addons/sale_rental/i18n/ko.po
odoo/addons/sale_rental/i18n/lt.po
odoo/addons/sale_rental/i18n/lt_LT.po
odoo/addons/sale_rental/i18n/lv.po
odoo/addons/sale_rental/i18n/mk.po
odoo/addons/sale_rental/i18n/mn.po
odoo/addons/sale_rental/i18n/nb.po
odoo/addons/sale_rental/i18n/nb_NO.po
odoo12_addon_sale_rental-12.0.1.1.1.dist-info/METADATA
odoo12_addon_sale_rental-12.0.1.1.1.dist-info/WHEEL
odoo12_addon_sale_rental-12.0.1.1.1.dist-info/top_level.txt
odoo12_addon_sale_rental-12.0.1.1.1.dist-info/RECORD
